spodgi/OdgiStore.py
spodgi/__init__.py
spodgi/terms.py
spodgi-0.0.2.dist-info/LICENSE
spodgi-0.0.2.dist-info/METADATA
spodgi-0.0.2.dist-info/WHEEL
spodgi-0.0.2.dist-info/entry_points.txt
spodgi-0.0.2.dist-info/top_level.txt
spodgi-0.0.2.dist-info/RECORD
