Metadata-Version: 2.1
Name: spodgi
Version: 0.0.2
Summary: rdflib extension adding genome graph ODGI back-end store
Home-page: http://github.com/JervenBolleman/spdogi
Author: Jerven Bolleman
Author-email: me@jerven.eu
License: MIT
Download-URL: https://github.com/JervenBolleman/spodgi/master
Platform: any
Classifier: Development Status :: 4 - Beta
Classifier: Programming Language :: Python
Classifier: Programming Language :: Python :: 3
Classifier: Programming Language :: Python :: 3.3
Classifier: Programming Language :: Python :: 3.4
Classifier: Programming Language :: Python :: 3.5
Classifier: Programming Language :: Python :: 3.6
Classifier: Programming Language :: Python :: 3.7
Classifier: License :: OSI Approved :: MIT License
Classifier: Topic :: Software Development :: Libraries :: Python Modules
Classifier: Operating System :: OS Independent
Classifier: Natural Language :: English
Requires-Python: >=3.6
Requires-Dist: Click (>=7.0.0)
Requires-Dist: rdflib (>=4.0)
